sep_eval/__init__.py
sep_eval/sep_eval.py
sep_eval/tests/__init__.py
sep_eval/tests/test_sep_eval.py
sep_eval-0.3.0.dist-info/LICENSE.md
sep_eval-0.3.0.dist-info/METADATA
sep_eval-0.3.0.dist-info/WHEEL
sep_eval-0.3.0.dist-info/top_level.txt
sep_eval-0.3.0.dist-info/RECORD
